LICENSE.txt
MANIFEST.in
README.rst
aws.py
setup.py
pyProj1.egg-info/PKG-INFO
pyProj1.egg-info/SOURCES.txt
pyProj1.egg-info/dependency_links.txt
pyProj1.egg-info/requires.txt
pyProj1.egg-info/top_level.txt