Metadata-Version: 1.1
Name: pyProj1
Version: 0.0.4
Summary: An demonstration of how to create, document, and publish to the cheese shop a5 pypi.org.
Home-page: http://packages.python.org/an_example_pypi_project
Author: vikash kumar
Author-email: vikash.kumar@brillio.com
License: BRILLIO
Keywords: example documentation tutorial
Platform: UNKNOWN
Classifier: Development Status :: 3 - Alpha
Classifier: Topic :: Utilities
Classifier: License :: OSI Approved :: MIT License
